gdb_remote_client/__init__.py
gdb_remote_client/client.py
gdb_remote_client/client_base.py
gdb_remote_client/errors.py
gdb_remote_client/utils.py
PyGdbRemoteClient-0.1.0.dist-info/LICENSE
PyGdbRemoteClient-0.1.0.dist-info/METADATA
PyGdbRemoteClient-0.1.0.dist-info/WHEEL
PyGdbRemoteClient-0.1.0.dist-info/top_level.txt
PyGdbRemoteClient-0.1.0.dist-info/RECORD
