Metadata-Version: 2.1
Name: PyGdbRemoteClient
Version: 0.1.0
Summary: GDB Remote client library for Python
Author-email: Jan Matyas <info@janmatyas.net>
Project-URL: Homepage, https://github.com/HonzaMat/PyGdbRemoteClient
Project-URL: Issues, https://github.com/HonzaMat/PyGdbRemoteClient/issues
Classifier: Programming Language :: Python :: 3
Classifier: License :: OSI Approved :: MIT License
Classifier: Operating System :: OS Independent
Requires-Python: >=3.7
License-File: LICENSE
